{
  "id": "633e2e6af570d10793afb812",
  "items_in_set": [
    {
      "id": "633e2e6af570d10793afb812",
      "url_name": "tatsu_prime_blade",
      "icon": "items/images/en/tatsu_prime_blade.d517fb4c89ed6076ddf26ffdb8efb88e.png",
      "sub_icon": "sub_icons/weapon/prime_blade_128x128.png",
      "thumb": "items/images/en/thumbs/tatsu_prime_blade.d517fb4c89ed6076ddf26ffdb8efb88e.128x128.png",
      "tags": [
        "component",
        "weapon",
        "prime"
      ],
      "ducats": 45,
      "rarity": "",
      "trading_tax": 2000
    },
    {
      "id": "633e2e6af570d10793afb817",
      "url_name": "tatsu_prime_set",
      "icon": "items/images/en/tatsu_prime_set.d517fb4c89ed6076ddf26ffdb8efb88e.png",
      "thumb": "items/images/en/thumbs/tatsu_prime_set.d517fb4c89ed6076ddf26ffdb8efb88e.128x128.png",
      "tags": [
        "weapon",
        "prime",
        "melee",
        "set"
      ],
      "ducats": 160,
      "rarity": "",
      "trading_tax": 6000
    },
    {
      "id": "633e2e6af570d10793afb818",
      "url_name": "tatsu_prime_blueprint",
      "icon": "items/images/en/tatsu_prime_blueprint.d517fb4c89ed6076ddf26ffdb8efb88e.png",
      "sub_icon": "sub_icons/blueprint_128x128.png",
      "thumb": "items/images/en/thumbs/tatsu_prime_blueprint.d517fb4c89ed6076ddf26ffdb8efb88e.128x128.png",
      "tags": [
        "melee",
        "weapon",
        "prime",
        "blueprint"
      ],
      "ducats": 15,
      "rarity": "",
      "trading_tax": 2000
    },
    {
      "id": "633e2e6bf570d10793afb81e",
      "url_name": "tatsu_prime_handle",
      "icon": "items/images/en/tatsu_prime_handle.d517fb4c89ed6076ddf26ffdb8efb88e.png",
      "sub_icon": "sub_icons/weapon/prime_handle_128x128.png",
      "thumb": "items/images/en/thumbs/tatsu_prime_handle.d517fb4c89ed6076ddf26ffdb8efb88e.128x128.png",
      "tags": [
        "component",
        "weapon",
        "prime"
      ],
      "ducats": 100,
      "rarity": "",
      "trading_tax": 2000
    }
  ]
}