{
  "id": "5f498a239426ed00443bd0bc",
  "items_in_set": [
    {
      "id": "5f498a239426ed00443bd0bc",
      "url_name": "vapor_trail",
      "icon": "items/images/en/vapor_trail.ebe940eeaf0b853890baa1a7b981d72c.png",
      "thumb": "items/images/en/thumbs/vapor_trail.ebe940eeaf0b853890baa1a7b981d72c.128x128.png",
      "mod_max_rank": 10,
      "tags": [
        "mod",
        "common",
        "k_drive"
      ],
      "ducats": 0,
      "rarity": "common",
      "trading_tax": 2000
    }
  ]
}